thompson_sampling/__init__.py
thompson_sampling/base.py
thompson_sampling/bernoulli.py
thompson_sampling/exponential.py
thompson_sampling/poisson.py
thompson_sampling/priors.py
thompson_sampling-0.0.4.dist-info/LICENSE.txt
thompson_sampling-0.0.4.dist-info/METADATA
thompson_sampling-0.0.4.dist-info/WHEEL
thompson_sampling-0.0.4.dist-info/top_level.txt
thompson_sampling-0.0.4.dist-info/RECORD
