Metadata-Version: 2.1
Name: thompson-sampling
Version: 0.0.4
Summary: Thompson Sampling
Home-page: https://github.com/Anton1o-I/thompson-sampling
Author: Anton1o-I
Author-email: a.iniguez21@gmail.com
License: LICENSE.txt
Platform: UNKNOWN
Requires-Dist: typing
Requires-Dist: numpy
Requires-Dist: seaborn
Requires-Dist: matplotlib
Requires-Dist: pandas
